Metadata-Version: 2.1
Name: odoo11-addon-report-hotel-reservation
Version: 11.0.1.0.0
Summary: Hotel Reservation Management - Reporting
Home-page: http://www.serpentcs.com
Author: Odoo Community Association (OCA), Serpent Consulting                Services Pvt. Ltd., Odoo S.A.
Author-email: support@odoo-community.org
License: AGPL-3
Platform: UNKNOWN
Classifier: Programming Language :: Python
Classifier: Framework :: Odoo
Classifier: License :: OSI Approved :: GNU Affero General Public License v3
Requires-Python: >=2.7, !=3.0.*, !=3.1.*, !=3.2.*, !=3.3.*, !=3.4.*
Requires-Dist: odoo11-addon-hotel-reservation
Requires-Dist: odoo (<11.1dev,>=11.0a)
